aipkgs_requests/__init__.py
aipkgs_requests/helpers.py
aipkgs_requests/helpers_session.py
aipkgs_requests/status.py
aipkgs_requests-1.0.6.dist-info/LICENSE.md
aipkgs_requests-1.0.6.dist-info/METADATA
aipkgs_requests-1.0.6.dist-info/WHEEL
aipkgs_requests-1.0.6.dist-info/RECORD
