Metadata-Version: 2.1
Name: aipkgs-requests
Version: 1.0.6
Summary: A package for requests
Home-page: https://gitlab.com/aipy/packages.git
License: MIT
Keywords: ai
Author: Alexy
Author-email: alexy.ib@outlook.com
Requires-Python: >=3.11.4,<4.0.0
Classifier: License :: OSI Approved :: MIT License
Classifier: Programming Language :: Python :: 3
Classifier: Programming Language :: Python :: 3.12
Requires-Dist: requests (>=2.31.0,<3.0.0)
Project-URL: Repository, https://gitlab.com/aipy/packages.git
